Metadata-Version: 2.1
Name: margo
Version: 0.0.4
Summary: A tool that generates yaml cell type marker which maps cell types to gene expression.
Home-page: https://github.com/camlab-bioml/margo
Author: Jinyu Hou
Author-email: jhou@lunenfeld.ca
License: GPLv2
Platform: UNKNOWN
Classifier: Programming Language :: Python :: 3
Classifier: License :: OSI Approved :: GNU General Public License v2 (GPLv2)
Classifier: Operating System :: OS Independent
Classifier: Topic :: Scientific/Engineering :: Bio-Informatics
